pyannote.pipeline-3.0.1-py3.11-nspkg.pth
pyannote/pipeline/__init__.py
pyannote/pipeline/_version.py
pyannote/pipeline/experiment.py
pyannote/pipeline/optimizer.py
pyannote/pipeline/parameter.py
pyannote/pipeline/pipeline.py
pyannote/pipeline/typing.py
pyannote/pipeline/blocks/__init__.py
pyannote/pipeline/blocks/classification.py
pyannote/pipeline/blocks/clustering.py
tests/__init__.py
tests/test_optimizer.py
tests/test_pipeline.py
tests/utils.py
pyannote.pipeline-3.0.1.dist-info/LICENSE
pyannote.pipeline-3.0.1.dist-info/METADATA
pyannote.pipeline-3.0.1.dist-info/WHEEL
pyannote.pipeline-3.0.1.dist-info/entry_points.txt
pyannote.pipeline-3.0.1.dist-info/namespace_packages.txt
pyannote.pipeline-3.0.1.dist-info/top_level.txt
pyannote.pipeline-3.0.1.dist-info/RECORD
